CHANGELOG.rst
DESCRIPTION.rst
LICENSE
MANIFEST.in
README.rst
setup.py
pyGeno/Chromosome.py
pyGeno/Exon.py
pyGeno/Gene.py
pyGeno/Genome.py
pyGeno/Protein.py
pyGeno/SNP.py
pyGeno/SNPFiltering.py
pyGeno/Transcript.py
pyGeno/__init__.py
pyGeno/bootstrap.py
pyGeno/configuration.py
pyGeno/pyGenoObjectBases.py
pyGeno.egg-info/PKG-INFO
pyGeno.egg-info/SOURCES.txt
pyGeno.egg-info/dependency_links.txt
pyGeno.egg-info/entry_points.txt
pyGeno.egg-info/requires.txt
pyGeno.egg-info/top_level.txt
pyGeno/examples/__init__.py
pyGeno/examples/bootstraping.py
pyGeno/examples/snps_queries.py
pyGeno/importation/Genomes.py
pyGeno/importation/SNPs.py
pyGeno/importation/__init__.py
pyGeno/tests/__init__.py
pyGeno/tests/test_csv.py
pyGeno/tests/test_genome.py
pyGeno/tools/BinarySequence.py
pyGeno/tools/ProgressBar.py
pyGeno/tools/SecureMmap.py
pyGeno/tools/SegmentTree.py
pyGeno/tools/SingletonManager.py
pyGeno/tools/Stats.py
pyGeno/tools/UsefulFunctions.py
pyGeno/tools/__init__.py
pyGeno/tools/io.py
pyGeno/tools/parsers/CSVTools.py
pyGeno/tools/parsers/CasavaTools.py
pyGeno/tools/parsers/FastaTools.py
pyGeno/tools/parsers/FastqTools.py
pyGeno/tools/parsers/GTFTools.py
pyGeno/tools/parsers/VCFTools.py
pyGeno/tools/parsers/__init__.py