Metadata-Version: 1.1
Name: pyGeno
Version: 2.0.0
Summary: A python package for Personalized Genomics and Proteomics
Home-page: http://pyGeno.iric.ca
Author: Tariq Daouda
Author-email: tariq.daouda@umontreal.ca
License: ApacheV2.0
Keywords: proteogenomics genomics proteomics annotations medicine research personalized gene sequence protein
Platform: UNKNOWN
Classifier: Development Status :: 5 - Production/Stable
Classifier: Intended Audience :: Science/Research
Classifier: Intended Audience :: Healthcare Industry
Classifier: Topic :: Scientific/Engineering :: Bio-Informatics
Classifier: Topic :: Software Development :: Libraries
Classifier: Topic :: Software Development :: Libraries :: Application Frameworks
Classifier: License :: OSI Approved :: Apache Software License
Classifier: Programming Language :: Python :: 3.7
